fitsviz/__init__.py
fitsviz/__main__.py
fitsviz/detection/__init__.py
fitsviz/detection/ap_photometry.py
fitsviz/detection/core.py
fitsviz/tests/__init__.py
fitsviz/tests/test_ap_photometry.py
fitsviz/tests/test_utils.py
fitsviz/utils/__init__.py
fitsviz/utils/cutils.py
fitsviz/viz/__init__.py
fitsviz/viz/plot_bokeh.py
fitsviz-1.2.2.dist-info/METADATA
fitsviz-1.2.2.dist-info/WHEEL
fitsviz-1.2.2.dist-info/entry_points.txt
fitsviz-1.2.2.dist-info/top_level.txt
fitsviz-1.2.2.dist-info/RECORD
