Metadata-Version: 2.1
Name: fitsviz
Version: 1.2.2
Summary: Autodetection of sources and visualization of FITS files
Author-email: Phani Velicheti <phaniv@arizona.edu>
Requires-Python: <3.12,>=3.8
Requires-Dist: pytest (==7.1.3)
Requires-Dist: poetry-core
Requires-Dist: astropy (>=5.3.1)
Requires-Dist: bokeh (>=3.2.0)
Requires-Dist: click (>=8.1.5)
Requires-Dist: dask (>=2023.5.0)
Requires-Dist: matplotlib (>=3.7.2)
Requires-Dist: numpy (>=1.20.1)
Requires-Dist: pandas (==1.5.3)
Requires-Dist: scipy (>=1.11.1)
Requires-Dist: photutils (>=1.8.0)
Requires-Dist: dask[distributed] (>=2023.7.0)
